portfolio/__init__.py
portfolio/admin.py
portfolio/forms.py
portfolio/models.py
portfolio/serializers.py
portfolio/urls.py
portfolio/views.py
portfolio/management/__init__.py
portfolio/management/commands/__init__.py
portfolio/management/commands/update_price_trackers.py
portfolio/management/commands/update_share_prices.py
portfolio/migrations/0001_initial.py
portfolio/migrations/0002_account_base_currency.py
portfolio/migrations/0003_auto_20150610_1811.py
portfolio/migrations/0004_auto_20150611_1029.py
portfolio/migrations/0005_price_currency.py
portfolio/migrations/0006_price_change.py
portfolio/migrations/0007_price_change_percentage.py
portfolio/migrations/0008_auto_20150923_1657.py
portfolio/migrations/0009_pricetracker.py
portfolio/migrations/0010_security_price_tracker.py
portfolio/migrations/0011_auto_20161210_1650.py
portfolio/migrations/__init__.py
portfolio/static/404.html
portfolio/static/apple-touch-icon-114x114-precomposed.png
portfolio/static/apple-touch-icon-57x57-precomposed.png
portfolio/static/apple-touch-icon-72x72-precomposed.png
portfolio/static/apple-touch-icon-precomposed.png
portfolio/static/apple-touch-icon.png
portfolio/static/index.html
portfolio/static/css/portfolio.css
portfolio/static/css/portfolio_styles.css
portfolio/static/css/style.css
portfolio/static/js/plugins.js
portfolio/static/js/portfolio-dividend-monthly.js
portfolio/static/js/portfolio.js
portfolio/static/js/portfolio_cumulative_dividend_chart.js
portfolio/static/js/script.js
portfolio/static/js/libs/jquery-1.7.1.js
portfolio/static/js/libs/jquery-1.7.1.min.js
portfolio/static/js/libs/modernizr-2.5.3.min.js
portfolio/static/js/portfolio/account.summary.controller.js
portfolio/static/js/portfolio/account.summary.module.js
portfolio/static/js/portfolio/config.route.js
portfolio/static/js/portfolio/constants.js
portfolio/static/js/portfolio/portfolio.config.js
portfolio/static/js/portfolio/portfolio2.module.js
portfolio/static/js/portfolio/positions.module.js
django_pj_portfolio-2.3.10.dist-info/AUTHORS.rst
django_pj_portfolio-2.3.10.dist-info/LICENSE
django_pj_portfolio-2.3.10.dist-info/METADATA
django_pj_portfolio-2.3.10.dist-info/WHEEL
django_pj_portfolio-2.3.10.dist-info/top_level.txt
django_pj_portfolio-2.3.10.dist-info/RECORD
