Metadata-Version: 2.1
Name: django-pj-portfolio
Version: 2.3.10
Summary: Portfolio tracking
Home-page: https://github.com/jokimies/django-pj-portfolio
Author: Petri Jokimies
Author-email: petri.jokimies@gmail.com
License: BSD
Keywords: django-pj-portfolio
Platform: UNKNOWN
Classifier: Development Status :: 3 - Alpha
Classifier: Framework :: Django
Classifier: Intended Audience :: Developers
Classifier: License :: OSI Approved :: BSD License
Classifier: Natural Language :: English
Classifier: Programming Language :: Python :: 2
Classifier: Programming Language :: Python :: 2.7
Classifier: Programming Language :: Python :: 3
Classifier: Programming Language :: Python :: 3.3
Classifier: Programming Language :: Python :: 3.4
License-File: LICENSE
License-File: AUTHORS.rst
